mygpoclient/__init__.py
mygpoclient/api.py
mygpoclient/api_test.py
mygpoclient/feeds.py
mygpoclient/http.py
mygpoclient/http_test.py
mygpoclient/json.py
mygpoclient/json_test.py
mygpoclient/locator.py
mygpoclient/locator_test.py
mygpoclient/public.py
mygpoclient/public_test.py
mygpoclient/simple.py
mygpoclient/simple_test.py
mygpoclient/testing.py
mygpoclient/util.py
mygpoclient-1.10.data/data/share/man/man1/mygpo-bpsync.1
mygpoclient-1.10.data/scripts/mygpo-bpsync
mygpoclient-1.10.data/scripts/mygpo-list-devices
mygpoclient-1.10.data/scripts/mygpo-simple-client
mygpoclient-1.10.dist-info/AUTHORS
mygpoclient-1.10.dist-info/COPYING
mygpoclient-1.10.dist-info/METADATA
mygpoclient-1.10.dist-info/WHEEL
mygpoclient-1.10.dist-info/top_level.txt
mygpoclient-1.10.dist-info/RECORD
