Metadata-Version: 2.1
Name: mygpoclient
Version: 1.10
Summary: gpodder.net API Client Library
Home-page: http://gpodder.org/mygpoclient/
Download-URL: http://gpodder.org/mygpoclient/mygpoclient-1.10.tar.gz
Author: Thomas Perl
Author-email: thp@gpodder.org
License: GNU General Public License v3 or later
Classifier: Development Status :: 5 - Production/Stable
Classifier: Intended Audience :: Developers
Classifier: License :: OSI Approved :: GNU General Public License v3 or later (GPLv3+)
Classifier: Operating System :: OS Independent
Classifier: Programming Language :: Python
Classifier: Programming Language :: Python :: 2
Classifier: Programming Language :: Python :: 2.6
Classifier: Programming Language :: Python :: 2.7
Classifier: Programming Language :: Python :: 3
Classifier: Programming Language :: Python :: 3.3
Classifier: Programming Language :: Python :: 3.4
License-File: COPYING
License-File: AUTHORS
